simple_terminal_banner/__init__.py
simple_terminal_banner/banner.py
simple_terminal_banner/examples.py
simple_terminal_banner-0.1.0.dist-info/LICENSE
simple_terminal_banner-0.1.0.dist-info/METADATA
simple_terminal_banner-0.1.0.dist-info/WHEEL
simple_terminal_banner-0.1.0.dist-info/top_level.txt
simple_terminal_banner-0.1.0.dist-info/RECORD
