Metadata-Version: 2.2
Name: simple_terminal_banner
Version: 0.1.0
Summary: A simple Python utility to display banners in the terminal
Author-email: "Stephen J. Graham" <stephen@seesawweb.com>
License: MIT
Project-URL: Homepage, https://github.com/charlbury/simple_terminal_banner
Project-URL: Repository, https://github.com/charlbury/simple_terminal_banner
Project-URL: Issues, https://github.com/charlbury/simple_terminal_banner/issues
Classifier: Programming Language :: Python :: 3
Classifier: License :: OSI Approved :: MIT License
Classifier: Operating System :: OS Independent
Requires-Python: >=3.7
License-File: LICENSE
